data_processing_ev/__init__.py
data_processing_ev/__main__.py
data_processing_ev/data_visualisation/__init__.py
data_processing_ev/data_visualisation/animation.py
data_processing_ev/data_visualisation/map_calcs.py
data_processing_ev/data_visualisation/mapping.py
data_processing_ev/ev_simulation/[deprecated]_charge_monitor_traffic.py
data_processing_ev/ev_simulation/__init__.py
data_processing_ev/ev_simulation/hull_ev_simulation.py
data_processing_ev/ev_simulation/results_splitter.py
data_processing_ev/ev_simulation/sumo_ev_simulation.py
data_processing_ev/helper_scripts/__init__.py
data_processing_ev/helper_scripts/energy_usage_boxplots_aggregator.py
data_processing_ev/helper_scripts/energy_usage_boxplots_aggregator_2.py
data_processing_ev/helper_scripts/mpl_figopen.py
data_processing_ev/helper_scripts/power_energy_plot_extractor.py
data_processing_ev/helper_scripts/__dirty/__init__.py
data_processing_ev/helper_scripts/__dirty/dirty_charging_potential.py
data_processing_ev/helper_scripts/__dirty/instructions.md
data_processing_ev/results_analysis/[deprecated]_data_analysis_new.py
data_processing_ev/results_analysis/[deprecated]_mk_output_dir.sh
data_processing_ev/results_analysis/[deprecated]_ren_output_dir.sh
data_processing_ev/results_analysis/[deprecated]_trash_output_dir.sh
data_processing_ev/results_analysis/__init__.py
data_processing_ev/results_analysis/analysis_functions.py
data_processing_ev/results_analysis/ev_box_plots.py
data_processing_ev/results_analysis/ev_results_analysis.py
data_processing_ev/results_analysis/pv_results_analysis.py
data_processing_ev/results_analysis/wind_results_analysis.py
data_processing_ev/routing/[deprecated]_charge_monitor.py
data_processing_ev/routing/[deprecated]_duarouter.sh
data_processing_ev/routing/__init__.py
data_processing_ev/routing/fcd_conversion.py
data_processing_ev/routing/routing.py
data_processing_ev/scenario_initialisation/__init__.py
data_processing_ev/scenario_initialisation/initialisation-instructions.md
ev_fleet_sim-1.12.3.post1.dist-info/LICENSE
ev_fleet_sim-1.12.3.post1.dist-info/METADATA
ev_fleet_sim-1.12.3.post1.dist-info/WHEEL
ev_fleet_sim-1.12.3.post1.dist-info/entry_points.txt
ev_fleet_sim-1.12.3.post1.dist-info/top_level.txt
ev_fleet_sim-1.12.3.post1.dist-info/RECORD
