Metadata-Version: 2.1
Name: ev-fleet-sim
Version: 1.12.3.post1
Summary: This software computes the electrical energy requirements of a fleet of vehicles. It also determines how much of this energy can be offset by renewable energy.
Home-page: https://ev-fleet-sim.online
Author: Chris Abraham
Author-email: chrisbrhm@gmail.com
Project-URL: Documentation, https://ev-fleet-sim.online/docs.html
Project-URL: Source, https://gitlab.com/eputs/ev-fleet-sim
Project-URL: Bug Tracker, https://gitlab.com/eputs/ev-fleet-sim/issues
Classifier: Programming Language :: Python :: 3
Classifier: License :: OSI Approved :: GNU General Public License v3 (GPLv3)
Classifier: Operating System :: OS Independent
Requires-Python: >=3.8
License-File: LICENSE
Requires-Dist: wheel
Requires-Dist: tqdm >=4.62.3
Requires-Dist: matplotlib ==3.3.4
Requires-Dist: pandas ==1.2.5
Requires-Dist: numpy >=1.19.5
Requires-Dist: scipy >=1.7.1
Requires-Dist: scikit-learn >=1.0.1
Requires-Dist: folium >=0.12.1
Requires-Dist: haversine >=2.5.1
Requires-Dist: rtree >=0.9.7
Requires-Dist: memory-profiler >=0.58.0
Requires-Dist: PyQt5 >=5.15.6
Requires-Dist: mpl-axes-aligner >=1.3
Requires-Dist: statsmodels >=0.13.0
Requires-Dist: area >=1.1.1
Requires-Dist: pdbpp >=0.10.3
Requires-Dist: build >=0.7.0
Requires-Dist: twine >=3.8.0
Requires-Dist: pyproj ==3.2.1
Requires-Dist: libsumo >=1.8.0
Requires-Dist: nautical-calculations
Requires-Dist: geopy
Requires-Dist: argcomplete
